<?xml version="1.0" encoding="UTF-8" ?> 
<bounds>
<points>
<p lng="28.96617" lat="60.34177" />
<p lng="28.96413" lat="60.34226" />
<p lng="28.94641" lat="60.34617" />
<p lng="28.94438" lat="60.34665" />
<p lng="28.93462" lat="60.34884" />
<p lng="28.93167" lat="60.34969" />
<p lng="28.92007" lat="60.35202" />
<p lng="28.91826" lat="60.35250" />
<p lng="28.91645" lat="60.35287" />
<p lng="28.89598" lat="60.35704" />
<p lng="28.89141" lat="60.35768" />
<p lng="28.87584" lat="60.35904" />
<p lng="28.86623" lat="60.36008" />
<p lng="28.84169" lat="60.36156" />
<p lng="28.83854" lat="60.36274" />
<p lng="28.82067" lat="60.36846" />
<p lng="28.81139" lat="60.37121" />
<p lng="28.80862" lat="60.37113" />
<p lng="28.79777" lat="60.37071" />
<p lng="28.79777" lat="60.37071" />
<p lng="28.79627" lat="60.36856" />
<p lng="28.79485" lat="60.36790" />
<p lng="28.79363" lat="60.36655" />
<p lng="28.79095" lat="60.36385" />
<p lng="28.78903" lat="60.36239" />
<p lng="28.78600" lat="60.36164" />
<p lng="28.78433" lat="60.36137" />
<p lng="28.78708" lat="60.36048" />
<p lng="28.78749" lat="60.35956" />
<p lng="28.78749" lat="60.35956" />
<p lng="28.78673" lat="60.35832" />
<p lng="28.78709" lat="60.35665" />
<p lng="28.78710" lat="60.35660" />
<p lng="28.78748" lat="60.35580" />
<p lng="28.78782" lat="60.35508" />
<p lng="28.78813" lat="60.35443" />
<p lng="28.79048" lat="60.35120" />
<p lng="28.79295" lat="60.35003" />
<p lng="28.79360" lat="60.34922" />
<p lng="28.79289" lat="60.34889" />
<p lng="28.79143" lat="60.34754" />
<p lng="28.79209" lat="60.34274" />
<p lng="28.79343" lat="60.34204" />
<p lng="28.79466" lat="60.33940" />
<p lng="28.79507" lat="60.33837" />
<p lng="28.79411" lat="60.33759" />
<p lng="28.79292" lat="60.33692" />
<p lng="28.79240" lat="60.33579" />
<p lng="28.79222" lat="60.33259" />
<p lng="28.79327" lat="60.33064" />
<p lng="28.79320" lat="60.32939" />
<p lng="28.79291" lat="60.32837" />
<p lng="28.79379" lat="60.32767" />
<p lng="28.79580" lat="60.32662" />
<p lng="28.79575" lat="60.32571" />
<p lng="28.79550" lat="60.32525" />
<p lng="28.79478" lat="60.32469" />
<p lng="28.79386" lat="60.32471" />
<p lng="28.78960" lat="60.32659" />
<p lng="28.78671" lat="60.32856" />
<p lng="28.78401" lat="60.32963" />
<p lng="28.78195" lat="60.32988" />
<p lng="28.78055" lat="60.32945" />
<p lng="28.77891" lat="60.32890" />
<p lng="28.77666" lat="60.32562" />
<p lng="28.77653" lat="60.32323" />
<p lng="28.77327" lat="60.32236" />
<p lng="28.77209" lat="60.32169" />
<p lng="28.77084" lat="60.31988" />
<p lng="28.76855" lat="60.32003" />
<p lng="28.76473" lat="60.32168" />
<p lng="28.76132" lat="60.32240" />
<p lng="28.76016" lat="60.32219" />
<p lng="28.75546" lat="60.32031" />
<p lng="28.75403" lat="60.31954" />
<p lng="28.75198" lat="60.31979" />
<p lng="28.75020" lat="60.32084" />
<p lng="28.74777" lat="60.32281" />
<p lng="28.74306" lat="60.32492" />
<p lng="28.73831" lat="60.32624" />
<p lng="28.73466" lat="60.32697" />
<p lng="28.73333" lat="60.32790" />
<p lng="28.72864" lat="60.33058" />
<p lng="28.72327" lat="60.33327" />
<p lng="28.70954" lat="60.33892" />
<p lng="28.70794" lat="60.33906" />
<p lng="28.70563" lat="60.33886" />
<p lng="28.70449" lat="60.33910" />
<p lng="28.70338" lat="60.33991" />
<p lng="28.69633" lat="60.34160" />
<p lng="28.69153" lat="60.34212" />
<p lng="28.68590" lat="60.34447" />
<p lng="28.68273" lat="60.34542" />
<p lng="28.67974" lat="60.34535" />
<p lng="28.67631" lat="60.34573" />
<p lng="28.67248" lat="60.34726" />
<p lng="28.67020" lat="60.34763" />
<p lng="28.66628" lat="60.34757" />
<p lng="28.66378" lat="60.34817" />
<p lng="28.65979" lat="60.35107" />
<p lng="28.65619" lat="60.35271" />
<p lng="28.64956" lat="60.35370" />
<p lng="28.64247" lat="60.35436" />
<p lng="28.63719" lat="60.35454" />
<p lng="28.63374" lat="60.35458" />
<p lng="28.63141" lat="60.35404" />
<p lng="28.62867" lat="60.35453" />
<p lng="28.62591" lat="60.35468" />
<p lng="28.62289" lat="60.35391" />
<p lng="28.62237" lat="60.35278" />
<p lng="28.62253" lat="60.35153" />
<p lng="28.62091" lat="60.35120" />
<p lng="28.61933" lat="60.35179" />
<p lng="28.61913" lat="60.35236" />
<p lng="28.61673" lat="60.35513" />
<p lng="28.61560" lat="60.35548" />
<p lng="28.61447" lat="60.35584" />
<p lng="28.61401" lat="60.35596" />
<p lng="28.61358" lat="60.35642" />
<p lng="28.62006" lat="60.35714" />
<p lng="28.62107" lat="60.35918" />
<p lng="28.62293" lat="60.35927" />
<p lng="28.62364" lat="60.35972" />
<p lng="28.62437" lat="60.36062" />
<p lng="28.62393" lat="60.36097" />
<p lng="28.62280" lat="60.36155" />
<p lng="28.61987" lat="60.36273" />
<p lng="28.61854" lat="60.36366" />
<p lng="28.61720" lat="60.36459" />
<p lng="28.61492" lat="60.36495" />
<p lng="28.61284" lat="60.36464" />
<p lng="28.61065" lat="60.36250" />
<p lng="28.60948" lat="60.36194" />
<p lng="28.60834" lat="60.36218" />
<p lng="28.60750" lat="60.36390" />
<p lng="28.60640" lat="60.36483" />
<p lng="28.60322" lat="60.36578" />
<p lng="28.60281" lat="60.36670" />
<p lng="28.60111" lat="60.36957" />
<p lng="28.59840" lat="60.37085" />
<p lng="28.59681" lat="60.37133" />
<p lng="28.59473" lat="60.37101" />
<p lng="28.59360" lat="60.37148" />
<p lng="28.59076" lat="60.37448" />
<p lng="28.58967" lat="60.37575" />
<p lng="28.58948" lat="60.37666" />
<p lng="28.58791" lat="60.37736" />
<p lng="28.58699" lat="60.37749" />
<p lng="28.58703" lat="60.37829" />
<p lng="28.58868" lat="60.37906" />
<p lng="28.58940" lat="60.37962" />
<p lng="28.58980" lat="60.38327" />
<p lng="28.58902" lat="60.38602" />
<p lng="28.58860" lat="60.38682" />
<p lng="28.58863" lat="60.38761" />
<p lng="28.59075" lat="60.38850" />
<p lng="28.59149" lat="60.38952" />
<p lng="28.59158" lat="60.39134" />
<p lng="28.59124" lat="60.39385" />
<p lng="28.59046" lat="60.39660" />
<p lng="28.58940" lat="60.39844" />
<p lng="28.58787" lat="60.40016" />
<p lng="28.58405" lat="60.40226" />
<p lng="28.57932" lat="60.40448" />
<p lng="28.57583" lat="60.40863" />
<p lng="28.57457" lat="60.41115" />
<p lng="28.57459" lat="60.41149" />
<p lng="28.57506" lat="60.41172" />
<p lng="28.57575" lat="60.41171" />
<p lng="28.57801" lat="60.41077" />
<p lng="28.57917" lat="60.41098" />
<p lng="28.57991" lat="60.41200" />
<p lng="28.57775" lat="60.41499" />
<p lng="28.57789" lat="60.41772" />
<p lng="28.57772" lat="60.41898" />
<p lng="28.57639" lat="60.42002" />
<p lng="28.57532" lat="60.42163" />
<p lng="28.57492" lat="60.42300" />
<p lng="28.57434" lat="60.42529" />
<p lng="28.57144" lat="60.42749" />
<p lng="28.56693" lat="60.42971" />
<p lng="28.56173" lat="60.43182" />
<p lng="28.55924" lat="60.43265" />
<p lng="28.55533" lat="60.43292" />
<p lng="28.55330" lat="60.43386" />
<p lng="28.55181" lat="60.43638" />
<p lng="28.54984" lat="60.43869" />
<p lng="28.54992" lat="60.44040" />
<p lng="28.54819" lat="60.44281" />
<p lng="28.54641" lat="60.44420" />
<p lng="28.53361" lat="60.45176" />
<p lng="28.53086" lat="60.45390" />
<p lng="28.53329" lat="60.45472" />
<p lng="28.53357" lat="60.45575" />
<p lng="28.53546" lat="60.45652" />
<p lng="28.53775" lat="60.45627" />
<p lng="28.53965" lat="60.45739" />
<p lng="28.54584" lat="60.46119" />
<p lng="28.54727" lat="60.46220" />
<p lng="28.54960" lat="60.46263" />
<p lng="28.55862" lat="60.46298" />
<p lng="28.56164" lat="60.46340" />
<p lng="28.56400" lat="60.46451" />
<p lng="28.56541" lat="60.46495" />
<p lng="28.58181" lat="60.46510" />
<p lng="28.58322" lat="60.46565" />
<p lng="28.58421" lat="60.46690" />
<p lng="28.58832" lat="60.46594" />
<p lng="28.59154" lat="60.46578" />
<p lng="28.59802" lat="60.46605" />
<p lng="28.60077" lat="60.46567" />
<p lng="28.60372" lat="60.46450" />
<p lng="28.60971" lat="60.46625" />
<p lng="28.61165" lat="60.46623" />
<p lng="28.61393" lat="60.46563" />
<p lng="28.61411" lat="60.46460" />
<p lng="28.61406" lat="60.46357" />
<p lng="28.61333" lat="60.46301" />
<p lng="28.61467" lat="60.46186" />
<p lng="28.61759" lat="60.46034" />
<p lng="28.62033" lat="60.45974" />
<p lng="28.62008" lat="60.45940" />
<p lng="28.62051" lat="60.45871" />
<p lng="28.62160" lat="60.45744" />
<p lng="28.62563" lat="60.45500" />
<p lng="28.63169" lat="60.45151" />
<p lng="28.63550" lat="60.44929" />
<p lng="28.63776" lat="60.44835" />
<p lng="28.63933" lat="60.44742" />
<p lng="28.64089" lat="60.44649" />
<p lng="28.64271" lat="60.44578" />
<p lng="28.64343" lat="60.44634" />
<p lng="28.64481" lat="60.44621" />
<p lng="28.64544" lat="60.44518" />
<p lng="28.64498" lat="60.44496" />
<p lng="28.64519" lat="60.44461" />
<p lng="28.64608" lat="60.44403" />
<p lng="28.64902" lat="60.44274" />
<p lng="28.64972" lat="60.44308" />
<p lng="28.65088" lat="60.44306" />
<p lng="28.65200" lat="60.44236" />
<p lng="28.65332" lat="60.44121" />
<p lng="28.65646" lat="60.43935" />
<p lng="28.65937" lat="60.43760" />
<p lng="28.66025" lat="60.43679" />
<p lng="28.66115" lat="60.43644" />
<p lng="28.66249" lat="60.43551" />
<p lng="28.66432" lat="60.43514" />
<p lng="28.66589" lat="60.43421" />
<p lng="28.66812" lat="60.43281" />
<p lng="28.66944" lat="60.43166" />
<p lng="28.67283" lat="60.43025" />
<p lng="28.67812" lat="60.42996" />
<p lng="28.68479" lat="60.42964" />
<p lng="28.68550" lat="60.42997" />
<p lng="28.68762" lat="60.43098" />
<p lng="28.68947" lat="60.43084" />
<p lng="28.69171" lat="60.42967" />
<p lng="28.69376" lat="60.42930" />
<p lng="28.69638" lat="60.43075" />
<p lng="28.69827" lat="60.43152" />
<p lng="28.70409" lat="60.43270" />
<p lng="28.70949" lat="60.43446" />
<p lng="28.71188" lat="60.43603" />
<p lng="28.71592" lat="60.43825" />
<p lng="28.71746" lat="60.44131" />
<p lng="28.71756" lat="60.44325" />
<p lng="28.71665" lat="60.44782" />
<p lng="28.71672" lat="60.44907" />
<p lng="28.71471" lat="60.45024" />
<p lng="28.71363" lat="60.45162" />
<p lng="28.71252" lat="60.45255" />
<p lng="28.71046" lat="60.45292" />
<p lng="28.71004" lat="60.45349" />
<p lng="28.70984" lat="60.45418" />
<p lng="28.70991" lat="60.45554" />
<p lng="28.70773" lat="60.45796" />
<p lng="28.70711" lat="60.45934" />
<p lng="28.70584" lat="60.46141" />
<p lng="28.70587" lat="60.46198" />
<p lng="28.70590" lat="60.46255" />
<p lng="28.70432" lat="60.46337" />
<p lng="28.70434" lat="60.46371" />
<p lng="28.70459" lat="60.46416" />
<p lng="28.70671" lat="60.46482" />
<p lng="28.70860" lat="60.46570" />
<p lng="28.70914" lat="60.46730" />
<p lng="28.70922" lat="60.46866" />
<p lng="28.70910" lat="60.47072" />
<p lng="28.70913" lat="60.47140" />
<p lng="28.70894" lat="60.47232" />
<p lng="28.70783" lat="60.47312" />
<p lng="28.70785" lat="60.47347" />
<p lng="28.70787" lat="60.47392" />
<p lng="28.70744" lat="60.47450" />
<p lng="28.70586" lat="60.47498" />
<p lng="28.70588" lat="60.47543" />
<p lng="28.70590" lat="60.47577" />
<p lng="28.70614" lat="60.47600" />
<p lng="28.70733" lat="60.47678" />
<p lng="28.70856" lat="60.47813" />
<p lng="28.70861" lat="60.47904" />
<p lng="28.70866" lat="60.48007" />
<p lng="28.70782" lat="60.48168" />
<p lng="28.70743" lat="60.48294" />
<p lng="28.70517" lat="60.48388" />
<p lng="28.70496" lat="60.48445" />
<p lng="28.70457" lat="60.48560" />
<p lng="28.70395" lat="60.48708" />
<p lng="28.70374" lat="60.48754" />
<p lng="28.70377" lat="60.48800" />
<p lng="28.70356" lat="60.48834" />
<p lng="28.70357" lat="60.48868" />
<p lng="28.70243" lat="60.48893" />
<p lng="28.70081" lat="60.48883" />
<p lng="28.69967" lat="60.48919" />
<p lng="28.69838" lat="60.49115" />
<p lng="28.69507" lat="60.49404" />
<p lng="28.69239" lat="60.49578" />
<p lng="28.69197" lat="60.49659" />
<p lng="28.69199" lat="60.49693" />
<p lng="28.69293" lat="60.49726" />
<p lng="28.69345" lat="60.49839" />
<p lng="28.69394" lat="60.49895" />
<p lng="28.69283" lat="60.49988" />
<p lng="28.69425" lat="60.50043" />
<p lng="28.69473" lat="60.50088" />
<p lng="28.69382" lat="60.50101" />
<p lng="28.69199" lat="60.50137" />
<p lng="28.69086" lat="60.50184" />
<p lng="28.68993" lat="60.50185" />
<p lng="28.68692" lat="60.50166" />
<p lng="28.68529" lat="60.50146" />
<p lng="28.68461" lat="60.50169" />
<p lng="28.68415" lat="60.50181" />
<p lng="28.68417" lat="60.50216" />
<p lng="28.68490" lat="60.50283" />
<p lng="28.68652" lat="60.50292" />
<p lng="28.68981" lat="60.50391" />
<p lng="28.68969" lat="60.50608" />
<p lng="28.68884" lat="60.50745" />
<p lng="28.68634" lat="60.50840" />
<p lng="28.68411" lat="60.50991" />
<p lng="28.68285" lat="60.51232" />
<p lng="28.68108" lat="60.51382" />
<p lng="28.67700" lat="60.51547" />
<p lng="28.67385" lat="60.51710" />
<p lng="28.67274" lat="60.51814" />
<p lng="28.67277" lat="60.51860" />
<p lng="28.67280" lat="60.51917" />
<p lng="28.67282" lat="60.51962" />
<p lng="28.67146" lat="60.52010" />
<p lng="28.67035" lat="60.52091" />
<p lng="28.66944" lat="60.52126" />
<p lng="28.66805" lat="60.52117" />
<p lng="28.66667" lat="60.52152" />
<p lng="28.66399" lat="60.52315" />
<p lng="28.66332" lat="60.52373" />
<p lng="28.66314" lat="60.52476" />
<p lng="28.66245" lat="60.52477" />
<p lng="28.66173" lat="60.52432" />
<p lng="28.65992" lat="60.52514" />
<p lng="28.66976" lat="60.52764" />
<p lng="28.67354" lat="60.52896" />
<p lng="28.67763" lat="60.52766" />
<p lng="28.68146" lat="60.52556" />
<p lng="28.68417" lat="60.52450" />
<p lng="28.68808" lat="60.52388" />
<p lng="28.69152" lat="60.52350" />
<p lng="28.69268" lat="60.52348" />
<p lng="28.69384" lat="60.52347" />
<p lng="28.69808" lat="60.52501" />
<p lng="28.69902" lat="60.52522" />
<p lng="28.70112" lat="60.52554" />
<p lng="28.70206" lat="60.52598" />
<p lng="28.70770" lat="60.52750" />
<p lng="28.70977" lat="60.52748" />
<p lng="28.72341" lat="60.52286" />
<p lng="28.72570" lat="60.52249" />
<p lng="28.73592" lat="60.52315" />
<p lng="28.74885" lat="60.52276" />
<p lng="28.75027" lat="60.52331" />
<p lng="28.75265" lat="60.52453" />
<p lng="28.75428" lat="60.52485" />
<p lng="28.76144" lat="60.52453" />
<p lng="28.76376" lat="60.52473" />
<p lng="28.76774" lat="60.52547" />
<p lng="28.77195" lat="60.52644" />
<p lng="28.77402" lat="60.52619" />
<p lng="28.77969" lat="60.52429" />
<p lng="28.79472" lat="60.51976" />
<p lng="28.79836" lat="60.51880" />
<p lng="28.79994" lat="60.51798" />
<p lng="28.82821" lat="60.49855" />
<p lng="28.83115" lat="60.49749" />
<p lng="28.82803" lat="60.49126" />
<p lng="28.82389" lat="60.48744" />
<p lng="28.82383" lat="60.48641" />
<p lng="28.82493" lat="60.48549" />
<p lng="28.83265" lat="60.48321" />
<p lng="28.84031" lat="60.47958" />
<p lng="28.84458" lat="60.47770" />
<p lng="28.84770" lat="60.47548" />
<p lng="28.84914" lat="60.47238" />
<p lng="28.85113" lat="60.47088" />
<p lng="28.85997" lat="60.46790" />
<p lng="28.86129" lat="60.46686" />
<p lng="28.86189" lat="60.46537" />
<p lng="28.86043" lat="60.45992" />
<p lng="28.86112" lat="60.45592" />
<p lng="28.86083" lat="60.45490" />
<p lng="28.85888" lat="60.45310" />
<p lng="28.85604" lat="60.45177" />
<p lng="28.85301" lat="60.45124" />
<p lng="28.84955" lat="60.45129" />
<p lng="28.84252" lat="60.44945" />
<p lng="28.84062" lat="60.44845" />
<p lng="28.83717" lat="60.44473" />
<p lng="28.83711" lat="60.44360" />
<p lng="28.84094" lat="60.43796" />
<p lng="28.84384" lat="60.43598" />
<p lng="28.84857" lat="60.43808" />
<p lng="28.85042" lat="60.43828" />
<p lng="28.85249" lat="60.43814" />
<p lng="28.85249" lat="60.43814" />
<p lng="28.85335" lat="60.43710" />
<p lng="28.85438" lat="60.43480" />
<p lng="28.85783" lat="60.43476" />
<p lng="28.85851" lat="60.43452" />
<p lng="28.85916" lat="60.43383" />
<p lng="28.86004" lat="60.43290" />
<p lng="28.86116" lat="60.43232" />
<p lng="28.86207" lat="60.43208" />
<p lng="28.86322" lat="60.43206" />
<p lng="28.86394" lat="60.43251" />
<p lng="28.86465" lat="60.43284" />
<p lng="28.86533" lat="60.43272" />
<p lng="28.86693" lat="60.43247" />
<p lng="28.87479" lat="60.42871" />
<p lng="28.87655" lat="60.42731" />
<p lng="28.87697" lat="60.42662" />
<p lng="28.87600" lat="60.42573" />
<p lng="28.87415" lat="60.42575" />
<p lng="28.87137" lat="60.42545" />
<p lng="28.86971" lat="60.42468" />
<p lng="28.86941" lat="60.42342" />
<p lng="28.87003" lat="60.42227" />
<p lng="28.87111" lat="60.42089" />
<p lng="28.87357" lat="60.41960" />
<p lng="28.87471" lat="60.41936" />
<p lng="28.87540" lat="60.41935" />
<p lng="28.87589" lat="60.41980" />
<p lng="28.87662" lat="60.42047" />
<p lng="28.87734" lat="60.42103" />
<p lng="28.87852" lat="60.42147" />
<p lng="28.88038" lat="60.42179" />
<p lng="28.88316" lat="60.42186" />
<p lng="28.88592" lat="60.42183" />
<p lng="28.88774" lat="60.42145" />
<p lng="28.88842" lat="60.42122" />
<p lng="28.88932" lat="60.42086" />
<p lng="28.89020" lat="60.42017" />
<p lng="28.89103" lat="60.41856" />
<p lng="28.89351" lat="60.41750" />
<p lng="28.89463" lat="60.41702" />
<p lng="28.89624" lat="60.41689" />
<p lng="28.89806" lat="60.41652" />
<p lng="28.89966" lat="60.41627" />
<p lng="28.90121" lat="60.41511" />
<p lng="28.90387" lat="60.41336" />
<p lng="28.90586" lat="60.41196" />
<p lng="28.90765" lat="60.41103" />
<p lng="28.91150" lat="60.40983" />
<p lng="28.91354" lat="60.40923" />
<p lng="28.91579" lat="60.40818" />
<p lng="28.91841" lat="60.40586" />
<p lng="28.92079" lat="60.40320" />
<p lng="28.92220" lat="60.39964" />
<p lng="28.92437" lat="60.39745" />
<p lng="28.92771" lat="60.39557" />
<p lng="28.92992" lat="60.39406" />
<p lng="28.93144" lat="60.39233" />
<p lng="28.93174" lat="60.38970" />
<p lng="28.93207" lat="60.38742" />
<p lng="28.93388" lat="60.38682" />
<p lng="28.93525" lat="60.38680" />
<p lng="28.93731" lat="60.38643" />
<p lng="28.93912" lat="60.38595" />
<p lng="28.94180" lat="60.38454" />
<p lng="28.94491" lat="60.38267" />
<p lng="28.94757" lat="60.38092" />
<p lng="28.95229" lat="60.37880" />
<p lng="28.95411" lat="60.37843" />
<p lng="28.95419" lat="60.37844" />
<p lng="28.94311" lat="60.37119" />
<p lng="28.94089" lat="60.36974" />
<p lng="28.94424" lat="60.36752" />
<p lng="28.94506" lat="60.36579" />
<p lng="28.94552" lat="60.36203" />
<p lng="28.94704" lat="60.36041" />
<p lng="28.95976" lat="60.35372" />
<p lng="28.96544" lat="60.34885" />
<p lng="28.96649" lat="60.34712" />
<p lng="28.96679" lat="60.34450" />
<p lng="28.96675" lat="60.34370" />
<p lng="28.96617" lat="60.34177" />
<p lng="28.96617" lat="60.34177" />
</points>
</bounds>